{"version":13,"data":{"renderViewState":{"leftEdgeTimeSec":0,"timeSecPerPixel":0.02248038441390461,"analogChannelViewStates":[{"index":0,"type":"Analog","stripchart":{"viewportCenterValue":2.5,"scalePerPixel":0.0625}},{"index":1,"type":"Analog","stripchart":{"viewportCenterValue":2.5,"scalePerPixel":0.0625}},{"index":2,"type":"Analog","stripchart":{"viewportCenterValue":2.5,"scalePerPixel":0.0625}},{"index":3,"type":"Analog","stripchart":{"viewportCenterValue":2.5,"scalePerPixel":0.0625}},{"index":4,"type":"Analog","stripchart":{"viewportCenterValue":2.5,"scalePerPixel":0.0625}},{"index":5,"type":"Analog","stripchart":{"viewportCenterValue":2.5,"scalePerPixel":0.0625}},{"index":6,"type":"Analog","stripchart":{"viewportCenterValue":2.5,"scalePerPixel":0.0625}},{"index":7,"type":"Analog","stripchart":{"viewportCenterValue":2.5,"scalePerPixel":0.0625}},{"index":8,"type":"Analog","stripchart":{"viewportCenterValue":2.5,"scalePerPixel":0.0625}},{"index":9,"type":"Analog","stripchart":{"viewportCenterValue":2.5,"scalePerPixel":0.0625}},{"index":10,"type":"Analog","stripchart":{"viewportCenterValue":2.5,"scalePerPixel":0.0625}},{"index":11,"type":"Analog","stripchart":{"viewportCenterValue":2.5,"scalePerPixel":0.0625}},{"index":12,"type":"Analog","stripchart":{"viewportCenterValue":2.5,"scalePerPixel":0.0625}},{"index":13,"type":"Analog","stripchart":{"viewportCenterValue":2.5,"scalePerPixel":0.0625}},{"index":14,"type":"Analog","stripchart":{"viewportCenterValue":2.5,"scalePerPixel":0.0625}},{"index":15,"type":"Analog","stripchart":{"viewportCenterValue":2.5,"scalePerPixel":0.0625}}]},"captureProgress":{"maxCollectedTime":27.808235520000004,"processedInterval":{"begin":0,"end":27.808235520000004},"memoryUsedMb":435.0421333312988,"isProcessing":false},"captureStartTime":{"unixTimeMilliseconds":1617696159137,"fractionalMilliseconds":0.847},"timingMarkers":{"markers":{},"pairs":{}},"measurements":[],"highLevelAnalyzers":[],"analyzers":[],"rowsSettings":[{"index":0,"type":"Digital","name":"Channel 0","height":100,"isHidden":false},{"index":1,"type":"Digital","name":"BCLK","height":100,"isHidden":false},{"index":2,"type":"Digital","name":"LRCLK","height":100,"isHidden":false},{"index":3,"type":"Digital","name":"DOUT","height":100,"isHidden":false},{"index":4,"type":"Digital","name":"ADBUS4 CS","height":100,"isHidden":false},{"index":5,"type":"Digital","name":"ADBUS2 SO","height":100,"isHidden":false},{"index":6,"type":"Digital","name":"ADBUS1 SI","height":100,"isHidden":false},{"index":7,"type":"Digital","name":"ADBUS0 SCK","height":100,"isHidden":false},{"index":8,"type":"Digital","name":"Channel 8","height":100},{"index":9,"type":"Digital","name":"Channel 9","height":100},{"index":10,"type":"Digital","name":"Channel 10","height":100},{"index":11,"type":"Digital","name":"Channel 11","height":100},{"index":12,"type":"Digital","name":"Channel 12","height":100},{"index":13,"type":"Digital","name":"Channel 13","height":100},{"index":14,"type":"Digital","name":"Channel 14","height":100},{"index":15,"type":"Digital","name":"Channel 15","height":100},{"index":0,"type":"Analog","name":"Channel 0","height":100,"isHidden":false},{"index":1,"type":"Analog","name":"BCLK","height":100},{"index":2,"type":"Analog","name":"LRCLK","height":100},{"index":3,"type":"Analog","name":"DOUT","height":100},{"index":4,"type":"Analog","name":"ADBUS4 CS","height":100},{"index":5,"type":"Analog","name":"ADBUS2 SO","height":100},{"index":6,"type":"Analog","name":"ADBUS1 SI","height":100},{"index":7,"type":"Analog","name":"ADBUS0 SCK","height":100},{"index":8,"type":"Analog","name":"Channel 8","height":100},{"index":9,"type":"Analog","name":"Channel 9","height":100},{"index":10,"type":"Analog","name":"Channel 10","height":100},{"index":11,"type":"Analog","name":"Channel 11","height":100},{"index":12,"type":"Analog","name":"Channel 12","height":100},{"index":13,"type":"Analog","name":"Channel 13","height":100},{"index":14,"type":"Analog","name":"Channel 14","height":100},{"index":15,"type":"Analog","name":"Channel 15","height":100}],"captureSettings":{"bufferSizeMb":3072,"captureMode":"Circular","stopAfterSeconds":100,"trimAfterCapture":false,"trimTimeSeconds":5,"digitalTriggerSettings":{"type":{"mode":"Edge","name":"Rising","pattern":"Rising"},"timeAfterTriggerToStop":1,"linkedChannels":{},"duration":{"min":0.001,"max":0.01},"selectedChannel":{"type":"Digital","index":1}},"glitchFilter":{"enabled":false,"channels":{"0":{"enabled":false,"widthSec":0.000001},"1":{"enabled":false,"widthSec":0.000001},"2":{"enabled":false,"widthSec":0.000001},"3":{"enabled":false,"widthSec":0.000001},"4":{"enabled":false,"widthSec":0.000001},"5":{"enabled":false,"widthSec":0.000001},"6":{"enabled":false,"widthSec":0.000001},"7":{"enabled":false,"widthSec":0.000001},"8":{"enabled":false,"widthSec":0.000001},"9":{"enabled":false,"widthSec":0.000001},"10":{"enabled":false,"widthSec":0.000001},"11":{"enabled":false,"widthSec":0.000001},"12":{"enabled":false,"widthSec":0.000001},"13":{"enabled":false,"widthSec":0.000001},"14":{"enabled":false,"widthSec":0.000001},"15":{"enabled":false,"widthSec":0.000001}}},"connectedDevice":{"name":"Logic 8","deviceId":"2303030794032701246","deviceType":"Logic8","isSimulation":false,"capabilities":{"channelCapabilities":[{"type":"Digital","index":0,"capability":"Toggleable"},{"type":"Digital","index":1,"capability":"Toggleable"},{"type":"Digital","index":2,"capability":"Toggleable"},{"type":"Digital","index":3,"capability":"Toggleable"},{"type":"Digital","index":4,"capability":"Toggleable"},{"type":"Digital","index":5,"capability":"Toggleable"},{"type":"Digital","index":6,"capability":"Toggleable"},{"type":"Digital","index":7,"capability":"Toggleable"},{"type":"Analog","index":0,"capability":"Toggleable"},{"type":"Analog","index":1,"capability":"Toggleable"},{"type":"Analog","index":2,"capability":"Toggleable"},{"type":"Analog","index":3,"capability":"Toggleable"},{"type":"Analog","index":4,"capability":"Toggleable"},{"type":"Analog","index":5,"capability":"Toggleable"},{"type":"Analog","index":6,"capability":"Toggleable"},{"type":"Analog","index":7,"capability":"Toggleable"}],"sampleRateOptions":[{"digital":100000000},{"digital":50000000},{"digital":40000000},{"digital":25000000},{"digital":20000000},{"digital":10000000},{"digital":8000000},{"digital":5000000},{"digital":4000000},{"digital":2000000},{"digital":1000000}],"isPhysicalDevice":true},"settings":{"enabledChannels":[{"type":"Digital","index":1},{"type":"Digital","index":2},{"type":"Digital","index":3}],"sampleRate":{"digital":50000000}}}},"digitalTriggerTime":-1,"name":"Session 0","dataTable":{"columns":{"analyzerIdentifier":{"isActive":true,"width":18,"isDefault":true,"baseKey":"analyzerIdentifier","excludeFromSearch":true},"frameType":{"isActive":true,"width":75,"isDefault":true,"baseKey":"frameType","excludeFromSearch":false,"isHidden":true},"start":{"isActive":true,"width":110,"isDefault":true,"baseKey":"start","excludeFromSearch":true,"isHidden":true},"duration":{"isActive":true,"width":80,"isDefault":true,"baseKey":"duration","excludeFromSearch":true,"isHidden":true},"data_mosi":{"width":75,"baseKey":"mosi","isActive":false},"data_miso":{"width":75,"baseKey":"miso","isActive":false,"isHidden":false},"data_error":{"width":75,"baseKey":"error","isActive":false},"data_channel":{"width":147,"baseKey":"channel","isActive":false},"data_data":{"width":183,"baseKey":"data","isActive":false}}},"analyzerTrigger":{"settings":{"enabled":false,"searchQuery":"","holdoffSeconds":0.2}},"timeManager":{"t0":{"type":"startOfCapture"}}},"binData":[{"type":"Digital","index":1,"file":"./digital-1.bin"},{"type":"Digital","index":2,"file":"./digital-2.bin"},{"type":"Digital","index":3,"file":"./digital-3.bin"}]}